{"event":"2025","members":{"2220651":{"completion_day_level":{},"local_score":0,"id":2220651,"name":"George Ontiveros","last_star_ts":0,"stars":0},"2583362":{"local_score":0,"completion_day_level":{},"stars":0,"last_star_ts":0,"name":"yaashaara","id":2583362},"2256044":{"last_star_ts":0,"name":"szuknome","stars":0,"id":2256044,"local_score":0,"completion_day_level":{}},"5167643":{"completion_day_level":{},"local_score":0,"id":5167643,"last_star_ts":0,"name":null,"stars":0},"3264098":{"completion_day_level":{},"local_score":0,"id":3264098,"name":"Seth","last_star_ts":0,"stars":0},"4510161":{"last_star_ts":0,"name":"Mitchell Foreman","stars":0,"id":4510161,"local_score":0,"completion_day_level":{}},"5167527":{"id":5167527,"stars":0,"last_star_ts":0,"name":"Jay Chung","completion_day_level":{},"local_score":0},"4274388":{"id":4274388,"stars":0,"last_star_ts":0,"name":"Julie McKenna","completion_day_level":{},"local_score":0},"4272186":{"local_score":0,"completion_day_level":{},"name":"Grady Griffin","last_star_ts":0,"stars":0,"id":4272186},"5166977":{"id":5166977,"name":"Jared B Glickfield","last_star_ts":0,"stars":0,"completion_day_level":{},"local_score":0},"2557432":{"local_score":0,"completion_day_level":{},"stars":0,"name":"eightB","last_star_ts":0,"id":2557432},"4774340":{"name":"dblatman1","last_star_ts":0,"stars":0,"id":4774340,"local_score":0,"completion_day_level":{}},"3421798":{"completion_day_level":{},"local_score":0,"id":3421798,"stars":0,"name":"Michael Hobbs","last_star_ts":0},"5160825":{"local_score":0,"completion_day_level":{},"stars":0,"name":"JGreinke","last_star_ts":0,"id":5160825},"4584484":{"last_star_ts":0,"name":"Greg McGuffey","stars":0,"id":4584484,"local_score":0,"completion_day_level":{}},"5167041":{"completion_day_level":{},"local_score":0,"id":5167041,"last_star_ts":0,"name":"Yajat Dewan","stars":0},"2260424":{"local_score":0,"completion_day_level":{},"stars":0,"last_star_ts":0,"name":"taryn","id":2260424},"4255689":{"local_score":0,"completion_day_level":{},"stars":0,"name":"Kelvin Pan","last_star_ts":0,"id":4255689},"4635707":{"local_score":0,"completion_day_level":{},"last_star_ts":0,"name":"Andrew Esparragoza","stars":0,"id":4635707},"4280427":{"completion_day_level":{},"local_score":0,"id":4280427,"last_star_ts":0,"name":"Jolene Yao","stars":0},"4272814":{"stars":0,"last_star_ts":0,"name":"JakeRapp20","id":4272814,"local_score":0,"completion_day_level":{}},"2256217":{"id":2256217,"stars":0,"last_star_ts":0,"name":"Jeb Baugh","completion_day_level":{},"local_score":0},"2313067":{"local_score":0,"completion_day_level":{},"name":"Mark Verdi","last_star_ts":0,"stars":0,"id":2313067},"2269921":{"completion_day_level":{},"local_score":0,"id":2269921,"name":"Jimmy Liang","last_star_ts":0,"stars":0},"5163536":{"id":5163536,"stars":0,"last_star_ts":0,"name":null,"completion_day_level":{},"local_score":0},"2255815":{"completion_day_level":{},"local_score":0,"id":2255815,"name":"Greg Quinlan","last_star_ts":0,"stars":0},"4273076":{"completion_day_level":{},"local_score":0,"id":4273076,"last_star_ts":0,"name":"AndrewMMartin","stars":0},"4633040":{"completion_day_level":{},"local_score":0,"id":4633040,"stars":0,"last_star_ts":0,"name":"Megan I"},"5167528":{"completion_day_level":{},"local_score":0,"id":5167528,"last_star_ts":0,"name":"Jon Legendre","stars":0},"5185062":{"id":5185062,"name":"Brandon Baker","last_star_ts":0,"stars":0,"completion_day_level":{},"local_score":0},"2194852":{"id":2194852,"stars":0,"name":"David Alexander","last_star_ts":0,"completion_day_level":{},"local_score":0},"1459499":{"completion_day_level":{},"local_score":0,"id":1459499,"stars":0,"name":"William Dorr","last_star_ts":0},"5167550":{"name":"Deepika Sahay","last_star_ts":0,"stars":0,"id":5167550,"local_score":0,"completion_day_level":{}},"4533109":{"id":4533109,"stars":0,"name":"Veronica Reyes","last_star_ts":0,"completion_day_level":{},"local_score":0},"5167803":{"id":5167803,"stars":0,"name":null,"last_star_ts":0,"completion_day_level":{},"local_score":0},"2289988":{"completion_day_level":{},"local_score":0,"id":2289988,"stars":0,"name":"Star-Lena Estock","last_star_ts":0},"5168385":{"id":5168385,"stars":0,"name":"Mark Conklin","last_star_ts":0,"completion_day_level":{},"local_score":0},"4256046":{"completion_day_level":{},"local_score":0,"id":4256046,"stars":0,"last_star_ts":0,"name":"John Pugh"},"5171267":{"local_score":0,"completion_day_level":{},"stars":0,"last_star_ts":0,"name":"Tanya Marsh Hofmann","id":5171267},"340478":{"id":340478,"last_star_ts":0,"name":"Jason Stevens","stars":0,"completion_day_level":{},"local_score":0},"4279535":{"completion_day_level":{},"local_score":0,"id":4279535,"last_star_ts":0,"name":"Lillianna","stars":0},"2268868":{"id":2268868,"stars":0,"name":"John Helt","last_star_ts":0,"completion_day_level":{},"local_score":0},"3268581":{"id":3268581,"stars":0,"last_star_ts":0,"name":"Scott Busche","completion_day_level":{},"local_score":0},"4683915":{"completion_day_level":{},"local_score":0,"id":4683915,"stars":0,"last_star_ts":0,"name":"Ricardo Winterstein"},"4272967":{"id":4272967,"stars":0,"name":"McGoffmann","last_star_ts":0,"completion_day_level":{},"local_score":0},"2255934":{"id":2255934,"name":"Glucky","last_star_ts":0,"stars":0,"completion_day_level":{},"local_score":0},"3264656":{"name":"Samson Joseph","last_star_ts":0,"stars":0,"id":3264656,"local_score":0,"completion_day_level":{}},"425763":{"completion_day_level":{},"local_score":0,"id":425763,"last_star_ts":0,"name":"Nathan Lacey","stars":0},"4508063":{"stars":0,"last_star_ts":0,"name":"pBragaDC","id":4508063,"local_score":0,"completion_day_level":{}},"2261264":{"local_score":442,"completion_day_level":{"1":{"1":{"star_index":0,"get_star_ts":1764565397},"2":{"star_index":3,"get_star_ts":1764565443}}},"last_star_ts":1764565443,"name":"rohnedwards","stars":2,"id":2261264},"140756":{"completion_day_level":{},"local_score":0,"id":140756,"stars":0,"name":"Chris Regan","last_star_ts":0},"2269330":{"id":2269330,"name":"Becky Valintakonis","last_star_ts":0,"stars":0,"completion_day_level":{},"local_score":0},"3264661":{"id":3264661,"last_star_ts":0,"name":"Matthew Kawamoto","stars":0,"completion_day_level":{},"local_score":0},"4507659":{"completion_day_level":{},"local_score":0,"id":4507659,"last_star_ts":0,"name":"Carly C","stars":0},"4265921":{"local_score":0,"completion_day_level":{},"stars":0,"name":"April Murphy","last_star_ts":0,"id":4265921},"5156549":{"id":5156549,"stars":0,"name":"Angela DeVilder","last_star_ts":0,"completion_day_level":{},"local_score":0},"4266383":{"id":4266383,"name":"Caro Peluso","last_star_ts":0,"stars":0,"completion_day_level":{},"local_score":0},"673727":{"local_score":0,"completion_day_level":{},"last_star_ts":0,"name":"Oliver Wilms","stars":0,"id":673727},"5155002":{"local_score":0,"completion_day_level":{},"stars":0,"last_star_ts":0,"name":"Shawn Craig","id":5155002},"4522978":{"last_star_ts":0,"name":null,"stars":0,"id":4522978,"local_score":0,"completion_day_level":{}},"917598":{"name":"Sam Holton","last_star_ts":0,"stars":0,"id":917598,"local_score":0,"completion_day_level":{}},"1789052":{"local_score":218,"completion_day_level":{"1":{"1":{"get_star_ts":1764565504,"star_index":4}}},"stars":1,"name":"Andrew Lin","last_star_ts":1764565504,"id":1789052},"5167799":{"local_score":0,"completion_day_level":{},"last_star_ts":0,"name":"Adrian Gordon","stars":0,"id":5167799},"4426449":{"stars":0,"last_star_ts":0,"name":"rkworth","id":4426449,"local_score":0,"completion_day_level":{}},"5138099":{"local_score":0,"completion_day_level":{},"name":"AFS AoC Bot","last_star_ts":0,"stars":0,"id":5138099},"4274336":{"last_star_ts":0,"name":"Jesse Berliner","stars":0,"id":4274336,"local_score":0,"completion_day_level":{}},"106934":{"stars":0,"name":"Stephen Carlon","last_star_ts":0,"id":106934,"local_score":0,"completion_day_level":{}},"3412554":{"completion_day_level":{},"local_score":0,"id":3412554,"stars":0,"name":"Nick O.","last_star_ts":0},"5163564":{"completion_day_level":{},"local_score":0,"id":5163564,"stars":0,"name":"GeethuM","last_star_ts":0},"2343976":{"name":"Tom Charles","last_star_ts":0,"stars":0,"id":2343976,"local_score":0,"completion_day_level":{}},"629425":{"id":629425,"name":"Dean Earl Wright","last_star_ts":0,"stars":0,"completion_day_level":{},"local_score":0},"5168309":{"completion_day_level":{},"local_score":0,"id":5168309,"last_star_ts":0,"name":"Ashley Ward","stars":0},"4508558":{"id":4508558,"stars":0,"name":"Garry Alcorn","last_star_ts":0,"completion_day_level":{},"local_score":0},"3252709":{"local_score":0,"completion_day_level":{},"name":"Jeff Maldonado","last_star_ts":0,"stars":0,"id":3252709},"2262523":{"completion_day_level":{},"local_score":0,"id":2262523,"name":"Ben Johnson","last_star_ts":0,"stars":0},"2519":{"completion_day_level":{},"local_score":0,"id":2519,"stars":0,"last_star_ts":0,"name":"John Herren"},"5173209":{"completion_day_level":{},"local_score":0,"id":5173209,"last_star_ts":0,"name":"min lee","stars":0},"2436853":{"local_score":0,"completion_day_level":{},"stars":0,"name":"Kevin Wei","last_star_ts":0,"id":2436853},"2257772":{"completion_day_level":{},"local_score":0,"id":2257772,"last_star_ts":0,"name":"Ariel Brest","stars":0},"5163167":{"id":5163167,"stars":0,"name":"Stephen Harper","last_star_ts":0,"completion_day_level":{},"local_score":0},"1538712":{"completion_day_level":{},"local_score":0,"id":1538712,"stars":0,"last_star_ts":0,"name":"Peter Schaefer"},"2266198":{"stars":0,"last_star_ts":0,"name":"anchoiniere","id":2266198,"local_score":0,"completion_day_level":{}},"5178508":{"completion_day_level":{},"local_score":0,"id":5178508,"stars":0,"last_star_ts":0,"name":"Alan"},"2255041":{"stars":0,"last_star_ts":0,"name":"Jared Patten","id":2255041,"local_score":0,"completion_day_level":{}},"198431":{"completion_day_level":{},"local_score":0,"id":198431,"stars":0,"last_star_ts":0,"name":"Greg Fuller"},"5157110":{"completion_day_level":{},"local_score":0,"id":5157110,"stars":0,"last_star_ts":0,"name":"Cortlan Edgett"},"485609":{"local_score":0,"completion_day_level":{},"stars":0,"last_star_ts":0,"name":"Arkady Pogostkin","id":485609},"2556370":{"local_score":0,"completion_day_level":{},"stars":0,"last_star_ts":0,"name":"Sam Cinco","id":2556370},"5157665":{"id":5157665,"name":"Aiden Snorek-Yates","last_star_ts":0,"stars":0,"completion_day_level":{},"local_score":0},"411281":{"completion_day_level":{},"local_score":0,"id":411281,"stars":0,"name":"jokajak","last_star_ts":0},"5166453":{"id":5166453,"name":"wizzy99","last_star_ts":0,"stars":0,"completion_day_level":{},"local_score":0},"108786":{"completion_day_level":{},"local_score":0,"id":108786,"stars":0,"last_star_ts":0,"name":"Ryan Widmaier"},"5173300":{"id":5173300,"name":"Andrew H","last_star_ts":0,"stars":0,"completion_day_level":{},"local_score":0},"4302515":{"local_score":0,"completion_day_level":{},"stars":0,"name":"Maliha Q","last_star_ts":0,"id":4302515},"5167233":{"last_star_ts":0,"name":"Zaria Fyffe","stars":0,"id":5167233,"local_score":0,"completion_day_level":{}},"5173044":{"id":5173044,"last_star_ts":0,"name":null,"stars":0,"completion_day_level":{},"local_score":0},"2255836":{"name":"Mary Kilbourne","last_star_ts":0,"stars":0,"id":2255836,"local_score":0,"completion_day_level":{}},"5163177":{"completion_day_level":{},"local_score":0,"id":5163177,"stars":0,"last_star_ts":0,"name":null},"2258355":{"completion_day_level":{},"local_score":0,"id":2258355,"stars":0,"name":"Ravi Raghunandan","last_star_ts":0},"4499317":{"last_star_ts":0,"name":"Nolan-Pye","stars":0,"id":4499317,"local_score":0,"completion_day_level":{}},"387988":{"local_score":0,"completion_day_level":{},"last_star_ts":0,"name":"Tucker Tibbetts","stars":0,"id":387988},"5154974":{"stars":0,"last_star_ts":0,"name":"Rachel Katsman","id":5154974,"local_score":0,"completion_day_level":{}},"3251140":{"stars":0,"name":"Lettie Ozuna","last_star_ts":0,"id":3251140,"local_score":0,"completion_day_level":{}},"4746926":{"id":4746926,"stars":0,"name":"Michelle Hong","last_star_ts":0,"completion_day_level":{},"local_score":0},"5156812":{"stars":0,"last_star_ts":0,"name":"mocaorsa","id":5156812,"local_score":0,"completion_day_level":{}},"5168245":{"stars":0,"last_star_ts":0,"name":null,"id":5168245,"local_score":0,"completion_day_level":{}},"4273617":{"stars":0,"name":"bek-afs","last_star_ts":0,"id":4273617,"local_score":0,"completion_day_level":{}},"5167792":{"completion_day_level":{"1":{"1":{"star_index":7,"get_star_ts":1764565763}}},"local_score":216,"id":5167792,"last_star_ts":1764565763,"name":"Ben Grafton","stars":1},"4272851":{"completion_day_level":{},"local_score":0,"id":4272851,"stars":0,"name":"Zardon Roger","last_star_ts":0},"5167513":{"local_score":0,"completion_day_level":{},"last_star_ts":0,"name":"Joshua Fankhauser","stars":0,"id":5167513},"4639190":{"completion_day_level":{},"local_score":0,"id":4639190,"last_star_ts":0,"name":"Brianna Navarro","stars":0},"4272025":{"completion_day_level":{},"local_score":0,"id":4272025,"stars":0,"last_star_ts":0,"name":"Kevin Cleveland"},"5156715":{"id":5156715,"last_star_ts":0,"name":"wan chen zhao","stars":0,"completion_day_level":{},"local_score":0},"4530506":{"local_score":0,"completion_day_level":{},"stars":0,"name":"Kristopher Duran","last_star_ts":0,"id":4530506},"4267057":{"id":4267057,"stars":0,"name":"Spencer Farfante","last_star_ts":0,"completion_day_level":{},"local_score":0},"2256122":{"name":"Michael Weglinski","last_star_ts":1764565688,"stars":1,"id":2256122,"local_score":217,"completion_day_level":{"1":{"1":{"get_star_ts":1764565688,"star_index":6}}}},"5156951":{"last_star_ts":0,"name":"Madison Hough","stars":0,"id":5156951,"local_score":0,"completion_day_level":{}},"2256015":{"local_score":0,"completion_day_level":{},"name":"ktruong5","last_star_ts":0,"stars":0,"id":2256015},"4274695":{"completion_day_level":{},"local_score":0,"id":4274695,"stars":0,"last_star_ts":0,"name":"jing yu"},"1180421":{"completion_day_level":{"1":{"1":{"get_star_ts":1764565401,"star_index":1}}},"local_score":220,"id":1180421,"stars":1,"last_star_ts":1764565401,"name":"David Hansen"},"1458161":{"last_star_ts":0,"name":"drewmathis","stars":0,"id":1458161,"local_score":0,"completion_day_level":{}},"5167705":{"id":5167705,"name":"Bryan","last_star_ts":0,"stars":0,"completion_day_level":{},"local_score":0},"3665945":{"id":3665945,"last_star_ts":0,"name":"Gustavo Paz","stars":0,"completion_day_level":{},"local_score":0},"3209687":{"local_score":0,"completion_day_level":{},"stars":0,"name":"bobbyhiddn","last_star_ts":0,"id":3209687},"2312905":{"name":"Steve Szczypinski","last_star_ts":0,"stars":0,"id":2312905,"local_score":0,"completion_day_level":{}},"1179903":{"completion_day_level":{},"local_score":0,"id":1179903,"name":"Shannon Briggs","last_star_ts":0,"stars":0},"2266236":{"name":"Brandon Slaght","last_star_ts":0,"stars":0,"id":2266236,"local_score":0,"completion_day_level":{}},"4272716":{"completion_day_level":{},"local_score":0,"id":4272716,"last_star_ts":0,"name":"Jerome Farley","stars":0},"5167514":{"id":5167514,"stars":0,"name":"Harrison Simmons","last_star_ts":0,"completion_day_level":{},"local_score":0},"4510953":{"completion_day_level":{},"local_score":0,"id":4510953,"last_star_ts":0,"name":"Ryan Merrell","stars":0},"1040031":{"local_score":0,"completion_day_level":{},"name":"Steve Keith","last_star_ts":0,"stars":0,"id":1040031},"4828137":{"completion_day_level":{},"local_score":0,"id":4828137,"stars":0,"name":"Isaac Ramirez","last_star_ts":0},"2257573":{"completion_day_level":{},"local_score":0,"id":2257573,"name":"tgonzales114","last_star_ts":0,"stars":0},"2255090":{"completion_day_level":{},"local_score":0,"id":2255090,"last_star_ts":0,"name":"Richard Bradley","stars":0},"5206694":{"id":5206694,"last_star_ts":0,"name":"RedSinder","stars":0,"completion_day_level":{},"local_score":0},"5171844":{"last_star_ts":0,"name":"Audrey Michaud","stars":0,"id":5171844,"local_score":0,"completion_day_level":{}},"5157163":{"local_score":0,"completion_day_level":{},"name":"Jim Stout","last_star_ts":0,"stars":0,"id":5157163},"4508145":{"id":4508145,"stars":0,"last_star_ts":0,"name":"August Lamb","completion_day_level":{},"local_score":0},"5185229":{"stars":0,"last_star_ts":0,"name":"Marina Orzechowski","id":5185229,"local_score":0,"completion_day_level":{}},"4574858":{"local_score":0,"completion_day_level":{},"stars":0,"name":"Jeb","last_star_ts":0,"id":4574858},"2257489":{"id":2257489,"stars":0,"name":"Evan Jones","last_star_ts":0,"completion_day_level":{},"local_score":0},"2256266":{"completion_day_level":{},"local_score":0,"id":2256266,"stars":0,"name":"Timothy Lefkowitz","last_star_ts":0},"4272999":{"id":4272999,"stars":0,"name":"Prabin Karki","last_star_ts":0,"completion_day_level":{},"local_score":0},"4532162":{"completion_day_level":{},"local_score":0,"id":4532162,"stars":0,"name":"Jacob Alarcon","last_star_ts":0},"4272714":{"completion_day_level":{},"local_score":0,"id":4272714,"last_star_ts":0,"name":"Michael Hahn","stars":0},"4509123":{"completion_day_level":{},"local_score":0,"id":4509123,"stars":0,"name":"Maddie Hickey","last_star_ts":0},"2271262":{"local_score":0,"completion_day_level":{},"stars":0,"last_star_ts":0,"name":"KengTeong","id":2271262},"5168134":{"id":5168134,"last_star_ts":0,"name":"Walter Cekala","stars":0,"completion_day_level":{},"local_score":0},"2553483":{"local_score":0,"completion_day_level":{},"stars":0,"last_star_ts":0,"name":"Devan","id":2553483},"4282178":{"local_score":0,"completion_day_level":{},"stars":0,"last_star_ts":0,"name":"Ivory Barksdale","id":4282178},"2271210":{"id":2271210,"last_star_ts":0,"name":"danielstich","stars":0,"completion_day_level":{},"local_score":0},"5163658":{"completion_day_level":{},"local_score":0,"id":5163658,"name":"Jackie","last_star_ts":0,"stars":0},"5167600":{"completion_day_level":{},"local_score":0,"id":5167600,"stars":0,"name":"Todd Emert","last_star_ts":0},"188044":{"id":188044,"name":"Elise Thorsen","last_star_ts":0,"stars":0,"completion_day_level":{},"local_score":0},"2256017":{"local_score":0,"completion_day_level":{},"stars":0,"name":"Jessica Carter","last_star_ts":0,"id":2256017},"4281479":{"completion_day_level":{},"local_score":0,"id":4281479,"stars":0,"last_star_ts":0,"name":"Erica White"},"973153":{"completion_day_level":{},"local_score":0,"id":973153,"stars":0,"last_star_ts":0,"name":"davidchiii"},"3467375":{"id":3467375,"name":"Abigail Urnes","last_star_ts":0,"stars":0,"completion_day_level":{},"local_score":0},"4585218":{"completion_day_level":{},"local_score":0,"id":4585218,"stars":0,"last_star_ts":0,"name":"Tatsiana Tsimafeyeva"},"3264493":{"local_score":0,"completion_day_level":{},"stars":0,"last_star_ts":0,"name":"Bhupendra Patidar","id":3264493},"3643290":{"name":null,"last_star_ts":0,"stars":0,"id":3643290,"local_score":0,"completion_day_level":{}},"2269946":{"id":2269946,"stars":0,"name":"Matthew Ludwig","last_star_ts":0,"completion_day_level":{},"local_score":0},"105906":{"local_score":439,"completion_day_level":{"1":{"2":{"star_index":5,"get_star_ts":1764565539},"1":{"star_index":2,"get_star_ts":1764565432}}},"stars":2,"name":"mherms","last_star_ts":1764565539,"id":105906},"5167838":{"stars":0,"last_star_ts":0,"name":null,"id":5167838,"local_score":0,"completion_day_level":{}},"4515963":{"local_score":0,"completion_day_level":{},"last_star_ts":0,"name":"Jeffrey Chase","stars":0,"id":4515963},"5156531":{"stars":0,"last_star_ts":0,"name":"Hannah Buckelew","id":5156531,"local_score":0,"completion_day_level":{}},"5157233":{"local_score":0,"completion_day_level":{},"name":"Abdullahi Ahmed","last_star_ts":0,"stars":0,"id":5157233},"5166939":{"completion_day_level":{},"local_score":0,"id":5166939,"stars":0,"name":"Christina Jiang","last_star_ts":0},"4635125":{"local_score":0,"completion_day_level":{},"stars":0,"name":"erika024","last_star_ts":0,"id":4635125},"5155105":{"id":5155105,"stars":0,"last_star_ts":0,"name":"Faith Van Kaiser","completion_day_level":{},"local_score":0},"2260783":{"name":"Lindsay Andersen","last_star_ts":0,"stars":0,"id":2260783,"local_score":0,"completion_day_level":{}},"2299938":{"name":"Carl Z.","last_star_ts":0,"stars":0,"id":2299938,"local_score":0,"completion_day_level":{}},"1852857":{"completion_day_level":{},"local_score":0,"id":1852857,"stars":0,"last_star_ts":0,"name":"Johnny Sor"},"5156497":{"id":5156497,"stars":0,"name":"Angelina Zabala","last_star_ts":0,"completion_day_level":{},"local_score":0},"5156512":{"last_star_ts":0,"name":"Ethan Cockrell","stars":0,"id":5156512,"local_score":0,"completion_day_level":{}},"5156859":{"name":"Jesse Berliner","last_star_ts":0,"stars":0,"id":5156859,"local_score":0,"completion_day_level":{}},"4745158":{"local_score":0,"completion_day_level":{},"name":"Boluwatife Olubi","last_star_ts":0,"stars":0,"id":4745158},"3191904":{"stars":0,"name":"artartar","last_star_ts":0,"id":3191904,"local_score":0,"completion_day_level":{}},"4685369":{"id":4685369,"name":"Catherine Moree","last_star_ts":0,"stars":0,"completion_day_level":{},"local_score":0},"3201672":{"stars":0,"name":"amfurst","last_star_ts":0,"id":3201672,"local_score":0,"completion_day_level":{}},"2258255":{"completion_day_level":{},"local_score":0,"id":2258255,"name":"anncduke","last_star_ts":0,"stars":0},"2326048":{"id":2326048,"stars":0,"last_star_ts":0,"name":"Paige N","completion_day_level":{},"local_score":0},"4510946":{"local_score":0,"completion_day_level":{},"stars":0,"name":"Erianna Jones","last_star_ts":0,"id":4510946},"5156554":{"local_score":0,"completion_day_level":{},"name":"Brianna Brown","last_star_ts":0,"stars":0,"id":5156554},"2256306":{"completion_day_level":{},"local_score":0,"id":2256306,"stars":0,"name":"John Childs","last_star_ts":0},"2258336":{"stars":0,"name":"Joe Fleming","last_star_ts":0,"id":2258336,"local_score":0,"completion_day_level":{}},"521159":{"last_star_ts":0,"name":"Jonathan Hill","stars":0,"id":521159,"local_score":0,"completion_day_level":{}},"2257934":{"local_score":0,"completion_day_level":{},"name":"Christina Varghese","last_star_ts":0,"stars":0,"id":2257934},"2257395":{"stars":0,"name":"Wesley Holevinski","last_star_ts":0,"id":2257395,"local_score":0,"completion_day_level":{}},"196733":{"last_star_ts":0,"name":"Justin Shirk","stars":0,"id":196733,"local_score":0,"completion_day_level":{}},"5167448":{"id":5167448,"name":"zain-safavi-usps","last_star_ts":0,"stars":0,"completion_day_level":{},"local_score":0},"3840593":{"completion_day_level":{},"local_score":0,"id":3840593,"stars":0,"name":"Michael Nguyen","last_star_ts":0},"2254145":{"id":2254145,"stars":0,"name":"JT Taylor","last_star_ts":0,"completion_day_level":{},"local_score":0},"4508550":{"last_star_ts":0,"name":"Darren Sims","stars":0,"id":4508550,"local_score":0,"completion_day_level":{}},"1503440":{"local_score":0,"completion_day_level":{},"stars":0,"last_star_ts":0,"name":"Sean Witte","id":1503440},"4509217":{"id":4509217,"stars":0,"last_star_ts":0,"name":"Davila Family","completion_day_level":{},"local_score":0},"5167495":{"stars":0,"name":"Shuchita Bora","last_star_ts":0,"id":5167495,"local_score":0,"completion_day_level":{}},"5172723":{"local_score":0,"completion_day_level":{},"last_star_ts":0,"name":"cipsys","stars":0,"id":5172723},"4502823":{"last_star_ts":0,"name":"Ahmad Ayub","stars":0,"id":4502823,"local_score":0,"completion_day_level":{}},"5156248":{"name":"Ketty Wilcoxen","last_star_ts":0,"stars":0,"id":5156248,"local_score":0,"completion_day_level":{}},"4282373":{"id":4282373,"last_star_ts":0,"name":"Nirajan Adhikari","stars":0,"completion_day_level":{},"local_score":0},"4671389":{"completion_day_level":{},"local_score":0,"id":4671389,"stars":0,"last_star_ts":0,"name":"amherms"},"5156804":{"stars":0,"last_star_ts":0,"name":"Brian S","id":5156804,"local_score":0,"completion_day_level":{}},"4577038":{"last_star_ts":0,"name":"Nikki Wang","stars":0,"id":4577038,"local_score":0,"completion_day_level":{}},"4516780":{"id":4516780,"name":"jperry92","last_star_ts":0,"stars":0,"completion_day_level":{},"local_score":0},"4667162":{"last_star_ts":0,"name":"Anderson Gonzalez","stars":0,"id":4667162,"local_score":0,"completion_day_level":{}},"4272713":{"local_score":0,"completion_day_level":{},"last_star_ts":0,"name":"MotoDragon MLM","stars":0,"id":4272713},"4273271":{"local_score":0,"completion_day_level":{},"stars":0,"name":"RS-1776","last_star_ts":0,"id":4273271},"2434026":{"stars":0,"last_star_ts":0,"name":"Sama Banya","id":2434026,"local_score":0,"completion_day_level":{}},"4002407":{"local_score":0,"completion_day_level":{},"name":"Matt Brandon","last_star_ts":0,"stars":0,"id":4002407},"14752":{"local_score":0,"completion_day_level":{},"name":"Ben Mendis","last_star_ts":0,"stars":0,"id":14752},"5008736":{"local_score":0,"completion_day_level":{},"name":"Andrew-b-Martin","last_star_ts":0,"stars":0,"id":5008736},"4511513":{"last_star_ts":0,"name":"Anthony Renninger","stars":0,"id":4511513,"local_score":0,"completion_day_level":{}},"4688646":{"last_star_ts":0,"name":"Michael Wilhelmi","stars":0,"id":4688646,"local_score":0,"completion_day_level":{}},"2256272":{"completion_day_level":{},"local_score":0,"id":2256272,"stars":0,"name":"Airica Gilliam","last_star_ts":0},"2264173":{"name":"Trevor Skelton","last_star_ts":0,"stars":0,"id":2264173,"local_score":0,"completion_day_level":{}},"2255902":{"completion_day_level":{},"local_score":0,"id":2255902,"last_star_ts":0,"name":"Steve Wuerthele","stars":0},"5167494":{"id":5167494,"stars":0,"name":"Abbey Ames","last_star_ts":0,"completion_day_level":{},"local_score":0},"4272734":{"local_score":0,"completion_day_level":{},"stars":0,"last_star_ts":0,"name":"Doug Woods","id":4272734},"3752645":{"id":3752645,"name":"lettie ozuna","last_star_ts":0,"stars":0,"completion_day_level":{},"local_score":0},"2258332":{"stars":0,"name":"rprtech","last_star_ts":0,"id":2258332,"local_score":0,"completion_day_level":{}}},"num_days":12,"owner_id":105906,"day1_ts":1764565200}